README.md
setup.py
api/__init__.py
api/v2ray/__init__.py
api/v2ray/config_pb2.py
api/v2ray/config_pb2_grpc.py
api/v2ray/app/__init__.py
api/v2ray/app/commander/__init__.py
api/v2ray/app/commander/config_pb2.py
api/v2ray/app/commander/config_pb2_grpc.py
api/v2ray/app/dispatcher/__init__.py
api/v2ray/app/dispatcher/config_pb2.py
api/v2ray/app/dispatcher/config_pb2_grpc.py
api/v2ray/app/dns/__init__.py
api/v2ray/app/dns/config_pb2.py
api/v2ray/app/dns/config_pb2_grpc.py
api/v2ray/app/log/__init__.py
api/v2ray/app/log/config_pb2.py
api/v2ray/app/log/config_pb2_grpc.py
api/v2ray/app/log/command/__init__.py
api/v2ray/app/log/command/config_pb2.py
api/v2ray/app/log/command/config_pb2_grpc.py
api/v2ray/app/policy/__init__.py
api/v2ray/app/policy/config_pb2.py
api/v2ray/app/policy/config_pb2_grpc.py
api/v2ray/app/proxyman/__init__.py
api/v2ray/app/proxyman/config_pb2.py
api/v2ray/app/proxyman/config_pb2_grpc.py
api/v2ray/app/proxyman/command/__init__.py
api/v2ray/app/proxyman/command/command_pb2.py
api/v2ray/app/proxyman/command/command_pb2_grpc.py
api/v2ray/app/reverse/__init__.py
api/v2ray/app/reverse/config_pb2.py
api/v2ray/app/reverse/config_pb2_grpc.py
api/v2ray/app/router/__init__.py
api/v2ray/app/router/config_pb2.py
api/v2ray/app/router/config_pb2_grpc.py
api/v2ray/app/router/command/__init__.py
api/v2ray/app/router/command/command_pb2.py
api/v2ray/app/router/command/command_pb2_grpc.py
api/v2ray/app/stats/__init__.py
api/v2ray/app/stats/config_pb2.py
api/v2ray/app/stats/config_pb2_grpc.py
api/v2ray/app/stats/command/__init__.py
api/v2ray/app/stats/command/command_pb2.py
api/v2ray/app/stats/command/command_pb2_grpc.py
api/v2ray/common/__init__.py
api/v2ray/common/log/__init__.py
api/v2ray/common/log/log_pb2.py
api/v2ray/common/log/log_pb2_grpc.py
api/v2ray/common/net/__init__.py
api/v2ray/common/net/address_pb2.py
api/v2ray/common/net/address_pb2_grpc.py
api/v2ray/common/net/destination_pb2.py
api/v2ray/common/net/destination_pb2_grpc.py
v2client.egg-info/PKG-INFO
v2client.egg-info/SOURCES.txt
v2client.egg-info/dependency_links.txt
v2client.egg-info/requires.txt
v2client.egg-info/top_level.txt
