Metadata-Version: 2.1
Name: v2client
Version: 1.1.1
Summary: A V2Ray/V2Fly client for Python
Home-page: https://github.com/its0x4d/v2client
Author: Mostafa Mosavi
Author-email: mostafa.uwsgi@gmail.com
License: MIT
Platform: UNKNOWN
Classifier: Programming Language :: Python :: 3
Classifier: License :: OSI Approved :: MIT License
Classifier: Operating System :: OS Independent
Requires-Python: >=3.6
